MANIFEST.in
README.rst
setup.py
test.py
quantumrandom/__init__.py
quantumrandom/cmd.py
quantumrandom/dev.py
quantumrandom.egg-info/PKG-INFO
quantumrandom.egg-info/SOURCES.txt
quantumrandom.egg-info/dependency_links.txt
quantumrandom.egg-info/entry_points.txt
quantumrandom.egg-info/top_level.txt
quantumrandom.egg-info/zip-safe