Metadata-Version: 1.1
Name: quantumrandom
Version: 1.6
Summary: A Python interface to the ANU Quantum Random Numbers Server
Home-page: http://github.com/lmacken/quantumrandom
Author: Luke Macken
Author-email: lmacken@redhat.com
License: MIT
Keywords: quantum random
Platform: UNKNOWN
Classifier: Development Status :: 5 - Production/Stable
Classifier: License :: OSI Approved :: MIT License
Classifier: Topic :: Scientific/Engineering :: Mathematics
